CDK_pywrapper/CDKdesc.jar
CDK_pywrapper/__init__.py
CDK_pywrapper/cdk_pywrapper.py
CDK_pywrapper/descs.json
CDK_pywrapper/utils.py
cdk_pywrapper-0.1.1.dist-info/licenses/LICENSE
cdk_pywrapper-0.1.1.dist-info/METADATA
cdk_pywrapper-0.1.1.dist-info/WHEEL
cdk_pywrapper-0.1.1.dist-info/top_level.txt
cdk_pywrapper-0.1.1.dist-info/RECORD
